swaggertest/__init__.py
swaggertest/app.py
swaggertest/command.py
swaggertest-0.1.1.dist-info/LICENSE
swaggertest-0.1.1.dist-info/METADATA
swaggertest-0.1.1.dist-info/WHEEL
swaggertest-0.1.1.dist-info/entry_points.txt
swaggertest-0.1.1.dist-info/top_level.txt
swaggertest-0.1.1.dist-info/RECORD
