Metadata-Version: 2.1
Name: swaggertest
Version: 0.1.1
Summary: Test your swagger spec
Home-page: https://github.com/Arborian/swaggertest
Author: Rick Copeland
Author-email: rick@arborian.co
License: UNKNOWN
Platform: UNKNOWN
Classifier: Programming Language :: Python :: 3
Classifier: Programming Language :: Python :: 3.7
Classifier: Programming Language :: Python :: 3.8
Requires-Dist: PyYAML
Requires-Dist: jsonref
Requires-Dist: jsonschema
Requires-Dist: jsonpointer
Requires-Dist: cliff
